wiki_scraper/__init__.py
wiki_scraper/myfunctions.py
wiki_scraper-0.1.0.dist-info/METADATA
wiki_scraper-0.1.0.dist-info/WHEEL
wiki_scraper-0.1.0.dist-info/top_level.txt
wiki_scraper-0.1.0.dist-info/RECORD
