Metadata-Version: 2.1
Name: wiki-scraper
Version: 0.1.0
Summary: UNKNOWN
Home-page: UNKNOWN
Author: Rigved Alankar
Author-email: rigvedalankar2000@gmail.com
License: MIT
Platform: UNKNOWN
Classifier: Intended Audience :: Developers
Classifier: License :: OSI Approved :: MIT License
Classifier: Programming Language :: Python
Classifier: Programming Language :: Python :: 3
Classifier: Programming Language :: Python :: 3.6
Classifier: Programming Language :: Python :: 3.7
Classifier: Programming Language :: Python :: 3.8
Classifier: Programming Language :: Python :: 3.9
Classifier: Operating System :: OS Independent
Requires-Dist: re
Requires-Dist: requests
Requires-Dist: nltk
Requires-Dist: bs4
